MANIFEST.in
README.md
setup.py
paraturegmailfeed/__init__.py
paraturegmailfeed/config.py
paraturegmailfeed/exceptions.py
paraturegmailfeed/feed.py
paraturegmailfeed/mongodao.py
paraturegmailfeed.egg-info/PKG-INFO
paraturegmailfeed.egg-info/SOURCES.txt
paraturegmailfeed.egg-info/dependency_links.txt
paraturegmailfeed.egg-info/not-zip-safe
paraturegmailfeed.egg-info/requires.txt
paraturegmailfeed.egg-info/top_level.txt
paraturegmailfeed/paratureaction/__init__.py
paraturegmailfeed/paratureaction/action.py
paraturegmailfeed/paratureaction/message.py
paraturegmailfeed/paratureaction/parser.py