Metadata-Version: 1.0
Name: paraturegmailfeed
Version: 0.65
Summary: ETL for Parature emails routed to Gmail account
Home-page: https://github.com/joelcolucci/paraturegmailfeed
Author: Joel Colucci
Author-email: joelcolucci@gmail.com
License: MIT
Platform: UNKNOWN
